setup.py
z2p/fileTools.py
z2p/pcAliveTools.py
z2p/portScanTools.py
z2p/scapyTools.py
z2p/threadTools.py
z2p.egg-info/PKG-INFO
z2p.egg-info/SOURCES.txt
z2p.egg-info/dependency_links.txt
z2p.egg-info/requires.txt
z2p.egg-info/top_level.txt