Metadata-Version: 1.2
Name: z2p
Version: 0.0.5
Summary: z2p's libarary 
Home-page: https://github.com/z2p
Author: z2p
Author-email: z2p0721@foxmail.com
License: UNKNOWN
Platform: UNKNOWN
Requires-Python: >=3
